<?xml version="1.0" encoding="utf-8" standalone="yes" ?>
<T3locallang>
	<meta type="array">
		<type>database</type>
		<description>Language labels for database tables/fields belonging to extension 'tcfilearchive'</description>
	</meta>
	<data type="array">
		<languageKey index="default" type="array">
			<label index="tx_tcfilearchive_content">Filearchive content</label>
			<label index="tx_tcfilearchive_content.title">Title</label>
			<label index="tx_tcfilearchive_content.type.I.0">Folder</label>
			<label index="tx_tcfilearchive_content.type.I.1">File</label>
			<label index="tx_tcfilearchive_content.type">Type</label>
			<label index="tx_tcfilearchive_content.path">Path</label>
		</languageKey>
		<languageKey index="dk" type="array">
			<label index="tx_tcfilearchive_content">Filarkiv indhold</label>
			<label index="tx_tcfilearchive_content.type.I.0">Mappe</label>
			<label index="tx_tcfilearchive_content.type.I.1">Fil</label>
			<label index="tx_tcfilearchive_content.type">Type</label>
			<label index="tx_tcfilearchive_content.path">Sti</label>
		</languageKey>
	</data>
</T3locallang>